lewis_lazy_logger/__init__.py
lewis_lazy_logger/logger.py
lewis_lazy_logger-0.1.1.dist-info/licenses/LICENSE
tests/test_logger.py
lewis_lazy_logger-0.1.1.dist-info/METADATA
lewis_lazy_logger-0.1.1.dist-info/WHEEL
lewis_lazy_logger-0.1.1.dist-info/top_level.txt
lewis_lazy_logger-0.1.1.dist-info/RECORD
