Metadata-Version: 2.4
Name: lewis-lazy-logger
Version: 0.1.1
Summary: A simple reusable logger setup
Author-email: Lewis Halstead <lewishalstead5@gmail.com>
Requires-Python: >=3.8
License-File: LICENSE
Requires-Dist: rich>=14.0.0
Dynamic: license-file
